pybudgetbook/.DS_Store
pybudgetbook/__init__.py
pybudgetbook/bb_io.py
pybudgetbook/fuzzy_match.py
pybudgetbook/image_filters.py
pybudgetbook/parsers.py
pybudgetbook/plotting.py
pybudgetbook/receipt.py
pybudgetbook/configs/__init__.py
pybudgetbook/configs/config.py
pybudgetbook/configs/config_template.ini
pybudgetbook/configs/config_tools.py
pybudgetbook/configs/constants.py
pybudgetbook/group_templates/item_groups_deu.json
pybudgetbook/group_templates/item_groups_eng.json
pybudgetbook/group_templates/item_groups_fra.json
pybudgetbook/group_templates/negative_match_deu.json
pybudgetbook/img/.DS_Store
pybudgetbook/img/add_row.png
pybudgetbook/img/classify.png
pybudgetbook/img/fill_data.png
pybudgetbook/img/load_rec.png
pybudgetbook/img/parse_data.png
pybudgetbook/img/parse_vendor.png
pybudgetbook/img/pie.png
pybudgetbook/img/reload_data.png
pybudgetbook/img/save.png
pybudgetbook/img/stem.png
pybudgetbook/img/tray_icon.svg
pybudgetbook/img/groups/alco.png
pybudgetbook/img/groups/bakery.png
pybudgetbook/img/groups/berry.png
pybudgetbook/img/groups/car.png
pybudgetbook/img/groups/dairy.png
pybudgetbook/img/groups/drinks.png
pybudgetbook/img/groups/drugstore.png
pybudgetbook/img/groups/fruit.png
pybudgetbook/img/groups/general.png
pybudgetbook/img/groups/house_gen.png
pybudgetbook/img/groups/kids.png
pybudgetbook/img/groups/sausage.png
pybudgetbook/img/groups/sweets.png
pybudgetbook/img/groups/veggies.png
pybudgetbook/ui/__init__.py
pybudgetbook/ui/main_gui.py
pybudgetbook/ui/main_gui.ui
pybudgetbook/ui/main_gui_cust.py
pybudgetbook/ui/start_gui.py
pybudgetbook/ui/ui_support.py
pybudgetbook-0.2.5.dist-info/entry_points.txt
pybudgetbook-0.2.5.dist-info/LICENSE.txt
pybudgetbook-0.2.5.dist-info/WHEEL
pybudgetbook-0.2.5.dist-info/METADATA
pybudgetbook-0.2.5.dist-info/RECORD
