Metadata-Version: 2.1
Name: pybudgetbook
Version: 0.2.5
Summary: Organize and sort your receipts locally, use pandas power to analyze your spendings!
Keywords: expenses,receipts,scan,shopping,financial,anlysis,pandas
Author-email: Max Elfner <max_elfner@gmx.net>
Requires-Python: >=3.8
Classifier: Development Status :: 4 - Beta
Classifier: Programming Language :: Python :: 3
Classifier: Operating System :: Microsoft :: Windows
Classifier: Operating System :: POSIX :: Linux
Classifier: Operating System :: MacOS :: MacOS X
Classifier: Natural Language :: English
Classifier: License :: OSI Approved :: MIT License
Requires-Dist: PySide6
Requires-Dist: numpy >= 1.20
Requires-Dist: appdirs
Requires-Dist: matplotlib >= 3.6
Requires-Dist: h5py >= 3.0
Requires-Dist: pandas >= 1.5
Requires-Dist: tables
Requires-Dist: scikit-image
Requires-Dist: Pillow
Requires-Dist: pytesseract
Requires-Dist: pypdfium2
Requires-Dist: darkdetect
Project-URL: Documentation, https://github.com/max3-2/pybudgetbook
Project-URL: Source, https://github.com/max3-2/pybudgetbook
